threadracer/__init__.py
threadracer/cli.py
threadracer/core/__init__.py
threadracer/core/downloader.py
threadracer/core/logger.py
threadracer/core/request.py
threadracer/spinner.py
threadracer/utils.py
threadracer-1.0.3.dist-info/WHEEL
threadracer-1.0.3.dist-info/entry_points.txt
threadracer-1.0.3.dist-info/METADATA
threadracer-1.0.3.dist-info/RECORD
