Metadata-Version: 2.4
Name: threadracer
Version: 1.0.3
Summary: Multithreaded file downloader
Author: Suryakant Upadhyay
Author-email: Suryakant Upadhyay <suryakantupadhyay18@gmail.com>
License-Expression: MIT
Requires-Dist: requests>=2.32.5
Requires-Dist: tqdm>=4.67.1
Requires-Python: >=3.12
